trapster/__init__.py
trapster/logger.py
trapster/trapster.py
trapster/ai/__init__.py
trapster/ai/base.py
trapster/ai/http.py
trapster/ai/ssh.py
trapster/data/trapster.conf
trapster/libs/__init__.py
trapster/libs/dns.py
trapster/libs/ldapasn1.py
trapster/modules/__init__.py
trapster/modules/base.py
trapster/modules/dns.py
trapster/modules/ftp.py
trapster/modules/http.py
trapster/modules/https.py
trapster/modules/ldap.py
trapster/modules/mssql.py
trapster/modules/mysql.py
trapster/modules/postgres.py
trapster/modules/rdp.py
trapster/modules/rsync.py
trapster/modules/snmp.py
trapster/modules/socks5.py
trapster/modules/ssh.py
trapster/modules/telnet.py
trapster/modules/vnc.py
trapster/modules/resources/VNC_ascii.hcchr
trapster-1.1.5.dist-info/licenses/LICENSE
trapster-1.1.5.dist-info/METADATA
trapster-1.1.5.dist-info/WHEEL
trapster-1.1.5.dist-info/entry_points.txt
trapster-1.1.5.dist-info/top_level.txt
trapster-1.1.5.dist-info/RECORD
