Metadata-Version: 2.4
Name: trapster
Version: 1.1.5
Summary: Trapster Daemon
Home-page: https://trapster.cloud/
Author: 0xBallpoint
Author-email: contact@ballpoint.fr
License: AGPL3
Keywords: trapster,honeypot,ballpoint,deceptive,security,network
Platform: linux
Classifier: Development Status :: 5 - Production/Stable
Classifier: Intended Audience :: Developers
Classifier: Framework :: AsyncIO
Classifier: Topic :: System :: Networking
Classifier: Topic :: Security
Classifier: Topic :: System :: Networking :: Monitoring
Classifier: Natural Language :: English
Classifier: Operating System :: POSIX :: Linux
Classifier: Programming Language :: Python :: 3
Classifier: Programming Language :: Python :: 3.11
Classifier: License :: OSI Approved :: GNU Affero General Public License v3 or later (AGPLv3+)
License-File: LICENSE
Requires-Dist: httpx>=0.27.0
Requires-Dist: psutil>=5.9.8
Requires-Dist: pyasn1>=0.4.8
Requires-Dist: redis>=5.0.4
Requires-Dist: cryptography>=43.0.1
Requires-Dist: asyncssh>=2.14.2
Requires-Dist: scapy>=2.5.0
Requires-Dist: jinja2>=3.1.4
Requires-Dist: PyYAML>=6.0.2
Requires-Dist: fastapi>=0.115.9
Requires-Dist: uvicorn>=0.34.0
Provides-Extra: ai
Requires-Dist: openai<1.99.0; extra == "ai"
Requires-Dist: openai-agents>=0.2.5; extra == "ai"
Dynamic: author
Dynamic: author-email
Dynamic: classifier
Dynamic: description
Dynamic: description-content-type
Dynamic: home-page
Dynamic: keywords
Dynamic: license
Dynamic: license-file
Dynamic: platform
Dynamic: provides-extra
Dynamic: requires-dist
Dynamic: summary
